{"solid":{"prefix":"fa-solid fa-","icon-style":"fa-solid","list-icon":"fa-solid fa-font-awesome","icons":["turn-up","hand-holding-medical","graduation-cap","video","plus-minus","barcode","square-share-nodes","jet-fighter","hand-point-left","kip-sign","masks-theater","d","umbrella","building-columns","users-gear","magnifying-glass-dollar","x","dollar-sign","turkish-lira-sign","print","exclamation","plane","face-sad-tear","user-injured","bone","bug-slash","note-sticky","magnet","1","square-full","stopwatch-20","cloud-sun","syringe","user-nurse","train-tram","user-large","ruler-vertical","magnifying-glass-minus","mask","brush","mug-saucer","window-minimize","file-invoice","hand-dots","user-clock","thumbs-up","magnifying-glass-plus","id-card-clip","earth-asia","hotel","9","gifts","circle-xmark","calendar-minus","bandage","brain","bowling-ball","dice","square-envelope","turn-down","face-grimace","arrows-up-down","water-ladder","calendar-day","hands","life-ring","money-bill-1-wave","align-right","dungeon","paper-plane","right-left","mask-face","share","database","triangle-exclamation","book-journal-whills","book-open","baht-sign","rectangle-xmark","cart-flatbed-suitcase","earth-europe","user-tag","image-portrait","briefcase","cloud-moon","hand-fist","diagram-successor","angle-left","battery-three-quarters","check","user-plus","book","comment-sms","table-list","4","m","desktop","shower","gauge-simple-high","scale-balanced","draw-polygon","rss","arrow-trend-down","cookie-bite","face-angry","border-all","anchor","book-quran","fire-flame-curved","arrow-up-z-a","clone","link-slash","hand-holding","face-grin-tongue-wink","circle-plus","shoe-prints","dragon","sd-card","bahai","trailer","calendar","cloud-moon-rain","up-down","fan","voicemail","infinity","chart-column","hippo","t","oil-can","up-right-and-down-left-from-center","hashtag","square-xmark","earth-oceania","gopuram","broom","person-biking","temperature-low","code-commit","music","yin-yang","cheese","wine-glass-empty","moon","carrot","dog","wand-magic","pen-nib","house-chimney-window","circle-chevron-left","golf-ball-tee","house-medical","arrow-up-short-wide","shield","file-export","face-grin-beam-sweat","clock-rotate-left","qrcode","angles-left","building","ticket-simple","award","arrow-turn-down","mercury","transgender","sim-card","dice-four","face-grin-hearts","splotch","warehouse","gears","peace","robot","spinner","rotate","hand-peace","hammer","person-praying","trophy","thumbtack","face-smile","truck-moving","percent","hand-middle-finger","vr-cardboard","thermometer","traffic-light","baby-carriage","battery-quarter","video-slash","pump-soap","car-rear","retweet","chevron-right","genderless","briefcase-medical","disease","hand-lizard","bacteria","chevron-left","holly-berry","drumstick-bite","angle-up","fill","tablet","bell-slash","bezier-curve","sign-hanging","arrow-trend-up","store","folder-minus","photo-film","rocket","map","shekel-sign","teeth","blender","equals","copyright","ruler-combined","trash-arrow-up","tractor","quote-left","baby","peso-sign","chalkboard-user","arrows-up-down-left-right","xmark","expand","plus","square-phone","2","gun","share-from-square","grip","hand-sparkles","volume-xmark","copy","diagram-project","baseball","circle-radiation","clapperboard","circle-half-stroke","user-graduate","fish","truck-fast","person-snowboarding","y","wind","user-shield","circle-user","list-check","shrimp","tv","arrow-up","brazilian-real-sign","chess-king","down-long","list-ul","code-compare","skull-crossbones","battery-full","chevron-down","suitcase-rolling","square-pen","receipt","cart-arrow-down","naira-sign","trash-can-arrow-up","person-dots-from-line","table-tennis-paddle-ball","magnifying-glass","rupiah-sign","font","play","ear-listen","link","boxes-stacked","star-half","check-to-slot","paragraph","fax","ice-cream","drum","person-walking-with-cane","hotdog","dharmachakra","bars-staggered","chess-rook","wine-bottle","hospital","envelope-open-text","gauge-high","section","inbox","socks","battery-empty","dove","earth-americas","eraser","droplet","arrow-down","person-swimming","greater-than","file","location-dot","handshake-angle","paint-roller","phone-slash","star-of-life","superscript","bell","temperature-full","podcast","square-h","bed","medal","dice-d20","book-open-reader","car","credit-card","bug","toolbox","kit-medical","chess-pawn","ellipsis","arrow-right-long","user-lock","thumbs-down","grip-lines","head-side-cough","angle-down","less-than","arrow-down-short-wide","florin-sign","circle-down","industry","horse-head","face-laugh-wink","guitar","sun","ruble-sign","yen-sign","toilet","mars","vault","bolt","caravan","file-arrow-down","compact-disc","upload","code-merge","stop","up-long","truck-pickup","tower-broadcast","skull","mill-sign","arrow-up-wide-short","utensils","rotate-right","arrow-right-arrow-left","kiwi-bird","dice-one","file-medical","b","laptop-medical","calendar-week","house","outdent","id-card","book-skull","align-center","face-meh","mobile","forward","hourglass-empty","eye-dropper","delete-left","face-grin","download","ship","cloud-rain","n","calculator","images","venus-double","person-hiking","closed-captioning","diagram-next","tty","flag-usa","right-long","power-off","ticket","ellipsis-vertical","wand-sparkles","flask","cent-sign","hamsa","map-pin","network-wired","folder-tree","sliders","khanda","coins","battery-half","piggy-bank","temperature-three-quarters","house-chimney-medical","caret-down","keyboard","timeline","s","baseball-bat-ball","faucet","pallet","backward-step","clock","square-root-variable","u","arrow-turn-up","grip-vertical","place-of-worship","vials","cart-shopping","star-of-david","mosque","droplet-slash","gear","hands-asl-interpreting","volume-off","franc-sign","street-view","arrow-left-long","chess","minus","virus-slash","dna","left-long","money-bill-1","crop-simple","indian-rupee-sign","chart-gantt","train-subway","circle-left","plane-arrival","calendar-plus","person-skiing-nordic","rectangle-list","dumbbell","face-grin-squint-tears","hard-drive","arrow-rotate-left","cookie","arrow-down-a-z","check-double","vest-patches","crosshairs","truck","landmark","prescription-bottle-medical","braille","calendar-check","water","hand-holding-droplet","arrow-down-1-9","sleigh","meteor","camera","cloud-meatball","circle-info","user-doctor","mountain","hourglass","indent","parachute-box","border-none","litecoin-sign","arrow-up-9-1","lungs","ribbon","paperclip","angles-up","envelope","cake-candles","comment","tag","satellite","lira-sign","child","hat-cowboy-side","phone-volume","table-cells-large","business-time","comment-dollar","person-dress","otter","user-secret","suitcase-medical","o","book-bible","file-pdf","table-cells","up-right-from-square","file-video","j","restroom","dice-d6","align-left","ruler","arrow-left","republican","hands-clapping","hands-holding","headphones","tenge-sign","divide","cubes","0","shirt","quote-right","poo","book-medical","gauge-simple","trash","pen-fancy","hat-wizard","text-width","person-booth","dice-six","shield-virus","door-closed","arrow-up-1-9","user-gear","head-side-virus","calendar-xmark","phone","face-grin-tears","lungs-virus","mars-double","location-crosshairs","biohazard","arrow-rotate-right","hands-praying","hand-scissors","drum-steelpan","hand-pointer","bacterium","hand-holding-dollar","face-grin-squint","diamond","comment-dots","sort-up","scale-unbalanced","vihara","floppy-disk","shop","prescription","face-frown","window-maximize","house-chimney","bus","signal","file-code","pen","user-slash","audio-description","face-sad-cry","eye","bus-simple","tape","basket-shopping","mobile-button","terminal","ban-smoking","cart-flatbed","bars-progress","square-parking","face-meh-blank","forward-fast","wine-glass","tags","shield-blank","teeth-open","comment-medical","panorama","route","cat","phone-flip","hat-cowboy","code-branch","handshake-slash","plane-departure","circle-question","file-image","rupee-sign","wrench","burger","file-audio","clipboard-check","wallet","volume-high","mobile-screen-button","circle-up","satellite-dish","basketball","trademark","plane-slash","user-astronaut","recycle","backward-fast","circle","square-poll-horizontal","elevator","lock-open","solar-panel","bitcoin-sign","cube","temperature-quarter","r","apple-whole","toilet-paper-slash","circle-pause","face-surprise","martini-glass-citrus","house-crack","dumpster-fire","house-user","mars-and-venus","heart","screwdriver-wrench","h","cash-register","signs-post","arrow-right","chart-line","object-group","face-rolling-eyes","circle-right","eject","helmet-safety","toilet-paper","kaaba","location-pin","poop","object-ungroup","face-grin-beam","file-contract","file-excel","bolt-lightning","chart-pie","taxi","road","leaf","f","austral-sign","virus-covid","won-sign","arrow-up-right-from-square","whiskey-glass","code","star-half-stroke","money-check","puzzle-piece","hand-holding-heart","house-chimney-user","up-down-left-right","file-signature","question","filter","face-kiss-wink-heart","language","bread-slice","vector-square","money-check-dollar","list-ol","sort","filter-circle-xmark","car-crash","circle-arrow-right","rectangle-ad","newspaper","snowflake","p","feather-pointed","a","person-skiing","z","democrat","comments-dollar","church","italic","cedi-sign","couch","martini-glass-empty","square","file-zipper","house-chimney-crack","archway","layer-group","virus","book-atlas","greater-than-equal","cruzeiro-sign","fire-extinguisher","arrows-rotate","guarani-sign","handshake-simple-slash","envelope-open","user-large-slash","chalkboard","cloud-arrow-down","arrows-left-right","file-powerpoint","file-word","face-smile-wink","text-slash","arrow-down-wide-short","candy-cane","circle-arrow-left","left-right","seedling","vest","palette","cloud-arrow-up","font-awesome","crutch","smog","face-tired","house-laptop","diamond-turn-right","subscript","scale-unbalanced-flip","address-card","registered","bomb","temperature-empty","pause","spa","scroll","box-open","square-arrow-up-right","file-import","circle-arrow-down","camera-retro","filter-circle-dollar","person-skating","suitcase","reply-all","certificate","arrow-down-long","user-tie","viruses","sterling-sign","lari-sign","circle-chevron-up","universal-access","face-laugh-beam","marker","id-badge","neuter","icicles","compass-drafting","circle-stop","circle-check","chair","euro-sign","ethernet","tablets","circle-play","cannabis","angles-right","snowplow","monument","minimize","smoking","dolly","gem","handshake","head-side-mask","lemon","table-columns","rotate-left","martini-glass","screwdriver","caret-up","3","microphone","image","frog","torii-gate","square-plus","window-restore","sailboat","crow","eye-low-vision","train","less-than-equal","hands-bubbles","chart-bar","square-caret-up","hand-back-fist","mars-stroke-right","chess-board","glasses","chess-queen","dice-two","gift","car-battery","mug-hot","square-poll-vertical","jedi","map-location-dot","border-top-left","not-equal","manat-sign","bold","stroopwafel","signature","user-pen","underline","bath","wifi","file-arrow-up","people-arrows-left-right","clipboard","champagne-glasses","mars-stroke-up","user-minus","store-slash","headset","colon-sign","unlock","pepper-hot","microphone-lines","city","code-fork","folder-open","face-laugh","shuttle-space","bed-pulse","fire","l","person-walking","toggle-on","circle-arrow-up","wheelchair","face-laugh-squint","chess-knight","arrow-up-a-z","user-group","weight-scale","file-prescription","weight-hanging","crown","microchip","temperature-high","people-carry-box","heart-pulse","passport","venus","right-to-bracket","blender-phone","hourglass-start","virus-covid-slash","server","shop-slash","arrow-right-to-bracket","computer-mouse","slash","spell-check","x-ray","file-invoice-dollar","spider","grip-lines-vertical","person-running","shuffle","shapes","charging-station","maximize","arrow-pointer","venus-mars","box","cross","repeat","star","spray-can-sparkles","camera-rotate","ban","chart-area","money-bill-wave","pizza-slice","tablet-button","c","location-arrow","synagogue","globe","bullhorn","key","highlighter","square-caret-left","van-shuttle","dumpster","user","pen-clip","e","wand-magic-sparkles","gauge","vial","mars-stroke","radiation","file-waveform","folder","arrow-up-from-bracket","hand-point-down","bacon","bullseye","umbrella-beach","6","align-justify","bookmark","money-bill","hand-point-up","face-frown-open","poo-storm","capsules","dong-sign","temperature-half","notes-medical","g","q","horse","angle-right","joint","igloo","school","mortar-pestle","snowman","truck-medical","head-side-cough-slash","bicycle","v","tooth","face-grin-wide","pills","hryvnia-sign","i","stairs","stamp","i-cursor","5","square-rss","dice-five","ear-deaf","face-grin-wink","chess-bishop","face-grin-tongue","face-kiss","stopwatch","hand-spock","chevron-up","plug","om","hand","eye-slash","users","mitten","arrow-down-z-a","bag-shopping","sink","microscope","share-nodes","car-side","pen-to-square","tree","map-location","hot-tub-person","gas-pump","lock","paintbrush","futbol","folder-plus","campground","egg","face-dizzy","circle-dot","gamepad","cart-plus","square-phone-flip","list","ghost","heading","peseta-sign","square-check","asterisk","ankh","compress","cloud-sun-rain","comment-slash","volume-low","feather","hanukiah","flag","memory","circle-dollar-to-slot","sitemap","headphones-simple","cloud-showers-heavy","unlock-keyhole","circle-chevron-down","arrow-right-from-bracket","circle-exclamation","caret-left","lightbulb","8","ruler-horizontal","film","face-kiss-beam","square-up-right","heart-crack","hourglass-end","bars","prescription-bottle","swatchbook","laptop-code","square-caret-down","compass","helicopter","square-minus","star-and-crescent","reply","clover","users-slash","tachograph-digital","table","hockey-puck","scissors","square-caret-right","pen-ruler","bell-concierge","motorcycle","box-tissue","microphone-slash","binoculars","gavel","hospital-user","face-flushed","cloud","paw","tablet-screen-button","circle-notch","rainbow","earth-africa","w","truck-monster","spray-can","face-grin-tongue-squint","arrow-down-9-1","box-archive","toggle-off","broom-ball","scroll-torah","user-ninja","7","blog","user-check","truck-ramp-box","clipboard-list","code-pull-request","paste","comments","caret-right","backward","pencil","k","strikethrough","address-book","pager","circle-h","envelopes-bulk","spoon","spaghetti-monster-flying","bong","face-grin-stars","record-vinyl","menorah","file-csv","laptop","person","fire-flame-simple","arrow-up-long","diagram-predecessor","beer-mug-empty","angles-down","crop","football","flag-checkered","face-smile-beam","forward-step","magnifying-glass-location","hand-point-right","fingerprint","pump-medical","microphone-lines-slash","icons","soap","atom","right-from-bracket","door-open","circle-minus","sort-down","volleyball","calendar-days","dice-three","ring","wave-square","file-lines","down-left-and-up-right-to-center","info","message","stethoscope","user-xmark","text-height","trash-can","at","circle-chevron-right","fill-drip"]},"regular":{"prefix":"fa-regular fa-","icon-style":"fa-regular","list-icon":"fa-regular fa-font-awesome","icons":["hand-point-left","face-sad-tear","note-sticky","square-full","window-minimize","thumbs-up","circle-xmark","calendar-minus","face-grimace","life-ring","paper-plane","rectangle-xmark","face-angry","clone","face-grin-tongue-wink","calendar","moon","face-grin-beam-sweat","building","face-grin-hearts","hand-peace","face-smile","hand-lizard","bell-slash","map","copyright","share-from-square","copy","circle-user","chess-king","star-half","chess-rook","hospital","file","bell","credit-card","chess-pawn","thumbs-down","circle-down","face-laugh-wink","sun","id-card","face-meh","face-grin","images","closed-captioning","keyboard","clock","money-bill-1","circle-left","calendar-plus","rectangle-list","face-grin-squint-tears","hard-drive","calendar-check","hourglass","envelope","comment","file-pdf","file-video","calendar-xmark","face-grin-tears","hand-scissors","hand-pointer","face-grin-squint","comment-dots","floppy-disk","face-frown","window-maximize","file-code","face-sad-cry","eye","face-meh-blank","circle-question","file-image","file-audio","circle-up","circle","circle-pause","face-surprise","heart","object-group","face-rolling-eyes","circle-right","object-ungroup","face-grin-beam","file-excel","star-half-stroke","face-kiss-wink-heart","newspaper","snowflake","square","file-zipper","envelope-open","file-powerpoint","file-word","face-smile-wink","font-awesome","face-tired","address-card","registered","face-laugh-beam","id-badge","circle-stop","circle-check","circle-play","gem","handshake","lemon","image","square-plus","window-restore","chart-bar","square-caret-up","hand-back-fist","chess-queen","clipboard","folder-open","face-laugh","face-laugh-squint","chess-knight","star","square-caret-left","user","folder","hand-point-down","bookmark","hand-point-up","face-frown-open","face-grin-wide","face-grin-wink","chess-bishop","face-grin-tongue","face-kiss","hand-spock","hand","eye-slash","pen-to-square","futbol","face-dizzy","circle-dot","square-check","flag","lightbulb","face-kiss-beam","square-caret-down","compass","square-minus","square-caret-right","face-flushed","face-grin-tongue-squint","paste","comments","address-book","face-grin-stars","face-smile-beam","hand-point-right","calendar-days","file-lines","message","trash-can"]},"brands":{"prefix":"fa-brands fa-","icon-style":"fa-brands","list-icon":"fa-brands fa-font-awesome","icons":["steam-symbol","pix","korvue","odnoklassniki-square","zhihu","intercom","google-pay","wodu","git-square","nutritionix","wordpress-simple","pushed","teamspeak","canadian-maple-leaf","ember","strava","creative-commons-sampling-plus","gulp","buy-n-large","wolf-pack-battalion","airbnb","mastodon","joomla","discourse","sitrox","critical-role","viacoin","pinterest-square","flipboard","mixcloud","amilia","medium","reacteurope","quora","vaadin","tumblr","usb","medrt","slack","edge-legacy","node-js","old-republic","telegram","internet-explorer","stumbleupon-circle","dribbble","btc","yammer","npm","buffer","pinterest","rockrms","twitter","jenkins","suse","replyd","behance-square","firefox-browser","skyatlas","youtube","alipay","php","github","uber","cc-amex","yandex-international","sketch","dev","git","ideal","js","hornbill","free-code-camp","bots","android","python","github-square","themeco","black-tie","leanpub","connectdevelop","weebly","grunt","perbyte","get-pocket","creative-commons-nc-jp","trello","goodreads-g","cpanel","deviantart","kaggle","staylinked","css3","rebel","supple","pied-piper-square","wix","rust","fantasy-flight-games","snapchat","cc-jcb","waze","fort-awesome","apper","pinterest-p","ns8","medapps","octopus-deploy","salesforce","buromobelexperte","wirsindhandwerk","sass","sellsy","html5","readme","yandex","kickstarter-k","pied-piper-hat","gg-circle","cc-diners-club","microblog","d-and-d","gitter","bluetooth","docker","jira","raspberry-pi","deezer","imdb","bitbucket","simplybuilt","servicestack","google-drive","line","viadeo","google-play","slideshare","whatsapp","autoprefixer","trade-federation","earlybirds","ussunnah","phabricator","fort-awesome-alt","uikit","jedi-order","gripfire","facebook","cmplid","instagram","dropbox","cc-amazon-pay","creative-commons-remix","figma","js-square","uniregistry","mendeley","vimeo","mixer","ravelry","twitch","deploydog","hubspot","linkedin","glide","linux","renren","dribbble-square","tiktok","steam-square","searchengin","xbox","resolving","superpowers","palfed","creative-commons-nd","elementor","stack-exchange","42-group","dashcube","cotton-bureau","erlang","bilibili","think-peaks","audible","facebook-messenger","etsy","maxcdn","symfony","tencent-weibo","digg","soundcloud","viber","flickr","blogger","cuttlefish","itunes","aviato","fly","optin-monster","spotify","magento","megaport","usps","cloudversify","wpforms","bandcamp","schlix","mizuni","forumbee","cloudscale","fulcrum","periscope","d-and-d-beyond","google-wallet","osi","first-order-alt","mandalorian","facebook-f","bimobject","gofore","ello","avianex","patreon","creative-commons-nc-eu","speaker-deck","ethereum","odnoklassniki","bootstrap","pied-piper-pp","affiliatetheme","dailymotion","yahoo","reddit-alien","typo3","gitlab","paypal","vine","opencart","blogger-b","less","quinscape","playstation","creative-commons-pd","blackberry","xing","dhl","gg","houzz","stripe","draft2digital","ubuntu","galactic-senate","umbraco","itch-io","opera","keycdn","bitcoin","xing-square","creative-commons-share","cc-stripe","squarespace","cc-paypal","react","hashnode","page4","themeisle","sith","jsfiddle","goodreads","linode","firefox","product-hunt","wordpress","pied-piper","studiovinari","envira","empire","y-combinator","angrycreative","speakap","angular","swift","researchgate","hackerrank","neos","shopify","phoenix-framework","fedex","stumbleupon","instagram-square","amazon-pay","padlet","apple-pay","keybase","gitkraken","hive","apple","reddit-square","gratipay","font-awesome","asymmetrik","500px","yarn","unsplash","amazon","ebay","accessible-icon","dochub","mdb","confluence","wpbeginner","cc-discover","app-store-ios","chrome","discord","reddit","behance","hips","creative-commons-zero","facebook-square","sticker-mule","bluetooth-b","hotjar","laravel","stripe-s","fedora","joget","skype","whatsapp-square","galactic-republic","angellist","wpressr","wikipedia-w","firstdraft","uncharted","weibo","grav","kickstarter","golang","itunes-note","cc-mastercard","app-store","fonticons-fi","ioxhost","accusoft","vuejs","freebsd","delicious","r-project","youtube-square","sellcast","expeditedssl","instalod","openid","scribd","cc-apple-pay","steam","mix","node","tumblr-square","codiepie","pied-piper-alt","vimeo-square","cloudsmith","adn","centos","meetup","wizards-of-the-coast","windows","rev","lyft","git-alt","codepen","twitter-square","shirtsinbulk","weixin","fonticons","watchman-monitoring","creative-commons","viadeo-square","adversal","creative-commons-sampling","hacker-news","evernote","chromecast","nimblr","digital-ocean","google-plus-square","linkedin-in","atlassian","square-font-awesome-stroke","google","safari","creative-commons-sa","red-river","algolia","pagelines","phoenix-squadron","github-alt","stack-overflow","foursquare","diaspora","google-plus","sourcetree","markdown","artstation","google-plus-g","napster","edge","hacker-news-square","the-red-yeti","battle-net","sistrix","lastfm-square","deskpro","square-font-awesome","contao","vimeo-v","css3-alt","snapchat-square","mailchimp","untappd","vk","rocketchat","whmcs","unity","creative-commons-by","hire-a-helper","drupal","glide-g","centercode","creative-commons-pd-alt","invision","java","orcid","qq","microsoft","vnv","guilded","modx","first-order","buysellads","stackpath","bity","dyalog","wpexplorer","ups","cloudflare","yoast","redhat","aws","creative-commons-nc","shopware","lastfm","cc-visa","yelp","hooli","monero"]}}